grounded_ai/__init__.py
grounded_ai/base.py
grounded_ai/schemas.py
grounded_ai/backends/__init__.py
grounded_ai/backends/anthropic.py
grounded_ai/backends/huggingface.py
grounded_ai/backends/openai.py
grounded_ai/backends/grounded_ai_slm/__init__.py
grounded_ai/backends/grounded_ai_slm/backend.py
grounded_ai/backends/grounded_ai_slm/prompts.py
grounded_ai/otel/__init__.py
grounded_ai/otel/converter.py
grounded_ai/otel/schemas.py
grounded_ai-1.0.9.dist-info/licenses/LICENSE
grounded_ai-1.0.9.dist-info/METADATA
grounded_ai-1.0.9.dist-info/WHEEL
grounded_ai-1.0.9.dist-info/top_level.txt
grounded_ai-1.0.9.dist-info/RECORD
