Metadata-Version: 2.4
Name: grounded-ai
Version: 1.0.9
Summary: A Python package for evaluating LLM application outputs.
Author-email: Josh Longenecker <support@groundedai.tech>
License: Copyright (c) 2018 The Python Packaging Authority
Project-URL: Homepage, https://github.com/grounded-ai/grounded_ai
Project-URL: Bug Tracker, https://github.com/grounded-ai/grounded_ai/issues
Keywords: NLP,QA,Toxicity,Rag,evaluation,language-model,transformer
Classifier: Development Status :: 5 - Production/Stable
Classifier: Intended Audience :: Science/Research
Classifier: License :: OSI Approved :: Apache Software License
Classifier: Operating System :: OS Independent
Classifier: Programming Language :: Python
Classifier: Programming Language :: Python :: 3
Classifier: Programming Language :: Python :: 3.8
Classifier: Programming Language :: Python :: 3.9
Classifier: Programming Language :: Python :: 3.10
Classifier: Topic :: Scientific/Engineering :: Artificial Intelligence
Requires-Python: >=3.8
License-File: LICENSE
Requires-Dist: pydantic>=2.0.0
Requires-Dist: jinja2>=3.1.6
Requires-Dist: openai>=1.0.0
Requires-Dist: anthropic>=0.7.0
Provides-Extra: slm
Requires-Dist: peft; extra == "slm"
Requires-Dist: transformers; extra == "slm"
Requires-Dist: torch>=2.0.0; extra == "slm"
Requires-Dist: accelerate; extra == "slm"
Requires-Dist: flash-attn; extra == "slm"
Requires-Dist: bitsandbytes; extra == "slm"
Dynamic: license-file
